hspipy/__init__.py
hspipy/db.csv
hspipy/hsp.py
hspipy/readers.py
hspipy/core/__init__.py
hspipy/core/hsp_estimator.py
hspipy/core/loss.py
hspipy/core/utils.py
hspipy/utils/__init__.py
hspipy/utils/discovery.py
hspipy-1.1.2.dist-info/licenses/LICENSE
tests/test_common.py
tests/test_discovery.py
hspipy-1.1.2.dist-info/METADATA
hspipy-1.1.2.dist-info/WHEEL
hspipy-1.1.2.dist-info/top_level.txt
hspipy-1.1.2.dist-info/RECORD
