Metadata-Version: 2.4
Name: HSPiPy
Version: 1.1.2
Summary: Hansen Solubility Parameters in Python
Author-email: Alejandro Gutierrez <agutierrez@g-npd.com>
License: MIT
Project-URL: Homepage, https://github.com/Gnpd/HSPiPy
Project-URL: Repository, https://github.com/Gnpd/HSPiPy
Project-URL: Issues, https://github.com/Gnpd/HSPiPy/issues
Keywords: hansen,solubility,parameters,chemistry,solvents
Classifier: Development Status :: 4 - Beta
Classifier: Intended Audience :: Developers
Classifier: Intended Audience :: Science/Research
Classifier: Topic :: Scientific/Engineering :: Chemistry
Classifier: Topic :: Software Development :: Libraries :: Python Modules
Classifier: License :: OSI Approved :: MIT License
Classifier: Programming Language :: Python :: 3.10
Classifier: Programming Language :: Python :: 3.11
Classifier: Programming Language :: Python :: 3.12
Requires-Python: >=3.10
License-File: LICENSE
Requires-Dist: scipy>=1.11.0
Requires-Dist: pandas>=1.0.0
Requires-Dist: matplotlib>=3.0.0
Requires-Dist: numpy>=1.18.0
Requires-Dist: scikit-learn>=1.6.0
Provides-Extra: test
Requires-Dist: pytest>=6.0; extra == "test"
Requires-Dist: pytest-cov>=2.0; extra == "test"
Provides-Extra: dev
Requires-Dist: pytest>=6.0; extra == "dev"
Requires-Dist: pytest-cov>=2.0; extra == "dev"
Requires-Dist: black>=22.0; extra == "dev"
Requires-Dist: flake8>=4.0; extra == "dev"
Requires-Dist: isort>=5.0; extra == "dev"
Dynamic: license-file
